homebak/__init__.py
homebak/cli.py
homebak/config.py
homebak/core.py
homebak/utils.py
homebak-0.1.0b5.dist-info/licenses/LICENSE
homebak-0.1.0b5.dist-info/METADATA
homebak-0.1.0b5.dist-info/WHEEL
homebak-0.1.0b5.dist-info/entry_points.txt
homebak-0.1.0b5.dist-info/top_level.txt
homebak-0.1.0b5.dist-info/RECORD
