Metadata-Version: 2.4
Name: homebak
Version: 0.1.0b5
Summary: Simple, configurable home directory backup tool
Author-email: Yigit Tuncer <yigittuncer@gmail.com>
License: MIT
Project-URL: Homepage, https://github.com/yigittuncer07/homebak
Project-URL: Repository, https://github.com/yigittuncer07/homebak
Project-URL: Issues, https://github.com/yigittuncer07/homebak/issues
Requires-Python: >=3.8
License-File: LICENSE
Requires-Dist: pyyaml
Requires-Dist: tqdm
Requires-Dist: platformdirs
Dynamic: license-file
